pdb2pqr/__init__.py
pdb2pqr/__main__.py
pdb2pqr/_version.py
pdb2pqr/aa.py
pdb2pqr/biomolecule.py
pdb2pqr/cells.py
pdb2pqr/cif.py
pdb2pqr/config.py
pdb2pqr/debump.py
pdb2pqr/definitions.py
pdb2pqr/forcefield.py
pdb2pqr/inputgen.py
pdb2pqr/io.py
pdb2pqr/main.py
pdb2pqr/na.py
pdb2pqr/pdb.py
pdb2pqr/psize.py
pdb2pqr/quatfit.py
pdb2pqr/residue.py
pdb2pqr/run.py
pdb2pqr/structures.py
pdb2pqr/topology.py
pdb2pqr/utilities.py
pdb2pqr/dat/AA.xml
pdb2pqr/dat/AMBER.DAT
pdb2pqr/dat/AMBER.names
pdb2pqr/dat/CHARMM.DAT
pdb2pqr/dat/CHARMM.names
pdb2pqr/dat/HYDROGENS.xml
pdb2pqr/dat/NA.xml
pdb2pqr/dat/PARSE.DAT
pdb2pqr/dat/PARSE.names
pdb2pqr/dat/PATCHES.xml
pdb2pqr/dat/PEOEPB.DAT
pdb2pqr/dat/PEOEPB.names
pdb2pqr/dat/SWANSON.DAT
pdb2pqr/dat/SWANSON.names
pdb2pqr/dat/TOPOLOGY.xml
pdb2pqr/dat/TYL06.DAT
pdb2pqr/dat/TYL06.names
pdb2pqr/hydrogens/__init__.py
pdb2pqr/hydrogens/optimize.py
pdb2pqr/hydrogens/structures.py
pdb2pqr/ligand/__init__.py
pdb2pqr/ligand/mol2.py
pdb2pqr/ligand/peoe.py
pdb2pqr/ligand/topology.py
pdb2pqr-3.7.1.dist-info/METADATA
pdb2pqr-3.7.1.dist-info/WHEEL
pdb2pqr-3.7.1.dist-info/entry_points.txt
pdb2pqr-3.7.1.dist-info/licenses/COPYING
pdb2pqr-3.7.1.dist-info/licenses/LICENSE.md
pdb2pqr-3.7.1.dist-info/RECORD
