Metadata-Version: 2.4
Name: pdb2pqr
Version: 3.7.1
Summary: Automates many of the common tasks of preparing structures for continuum solvation calculations as well as many other types of biomolecular structure modeling, analysis, and simulation.
Project-URL: Homepage, https://www.poissonboltzmann.org
Project-URL: Documentation, https://pdb2pqr.readthedocs.io/
Project-URL: Get help, https://github.com/Electrostatics/pdb2pqr/issues
Project-URL: Publications, https://pubmed.ncbi.nlm.nih.gov/?term=R01+GM069702
Project-URL: Funding, https://bit.ly/apbs-funding
Project-URL: Source, https://github.com/Electrostatics/pdb2pqr
Author: Jens Erik Nielsen
Author-email: Nathan Baker <nathanandrewbaker@gmail.com>
License: Copyright (c) 2002-2024, Jens Erik Nielsen; Nathan A. Baker; Battelle Memorial Institute, Developed at the Pacific Northwest National Laboratory, operated by Battelle Memorial Institute, Pacific Northwest Division for the U.S. Department Energy.; Paul Czodrowski & Gerhard Klebe, University of Marburg.
License-File: COPYING
License-File: LICENSE.md
Keywords: chemistry,molecular biology,science
Classifier: Development Status :: 4 - Beta
Classifier: Environment :: Console
Classifier: Intended Audience :: Science/Research
Classifier: License :: OSI Approved :: BSD License
Classifier: Natural Language :: English
Classifier: Operating System :: MacOS
Classifier: Operating System :: Microsoft :: Windows
Classifier: Operating System :: POSIX
Classifier: Programming Language :: Python
Classifier: Programming Language :: Python :: 3.11
Classifier: Programming Language :: Python :: 3.12
Classifier: Programming Language :: Python :: 3.13
Classifier: Programming Language :: Python :: Implementation :: CPython
Classifier: Topic :: Scientific/Engineering :: Bio-Informatics
Classifier: Topic :: Scientific/Engineering :: Chemistry
Requires-Python: <4,>=3.11
Requires-Dist: docutils<0.18
Requires-Dist: mmcif-pdbx>=1.1.2
Requires-Dist: numpy
Requires-Dist: propka>=3.5
Requires-Dist: requests
Provides-Extra: dev
Requires-Dist: check-manifest; extra == 'dev'
Provides-Extra: test
Requires-Dist: coverage; extra == 'test'
Requires-Dist: pandas>=1.0; extra == 'test'
Requires-Dist: pytest; extra == 'test'
Requires-Dist: ruff; extra == 'test'
Requires-Dist: testfixtures; extra == 'test'
